greenpeace/__init__.py
greenpeace/greenpeace.py
greenpeace/import_inspector.py
greenpeace/pypi_server.py
greenpeace/requirements.py
tests/__init__.py
tests/test_greenpeace.py
tests/test_import_inspector.py
tests/test_pypi_server.py
tests/test_requirements.py
greenpeace-0.2.dist-info/LICENSE
greenpeace-0.2.dist-info/METADATA
greenpeace-0.2.dist-info/WHEEL
greenpeace-0.2.dist-info/top_level.txt
greenpeace-0.2.dist-info/RECORD
