Metadata-Version: 2.1
Name: greenpeace
Version: 0.2
Summary: Python environment clean up.
Home-page: https://github.com/fdieulle/greenpeace
Author: Fabien Dieulle
Author-email: fabiendieulle@hotmail.fr
License: UNKNOWN
Platform: UNKNOWN
Classifier: License :: OSI Approved :: MIT License
Classifier: Operating System :: OS Independent
Classifier: Programming Language :: Python :: 3.6
Classifier: Programming Language :: Python :: 3.7
Classifier: Programming Language :: Python :: 3.8
Classifier: Programming Language :: Python :: 3.9
Requires-Dist: requests
Requires-Dist: yarg
